{"tables":[{"rowIndex":0,"content":{"1":"DATE","2":"AIRCRAFT TYPE","3":"AIRCRAFT IDENT","4":"FROM","5":"TO","6":"NR INST. APP.","7":"REMARKS AND ENDORSEMENTS","8":"NR T/O","9":"NR LDG","10":"SINGLE-ENGINE LAND","11":"SINGLE-ENGINE LAND","12":"MULTI-ENGINE LAND","13":"MULTI-ENGINE LAND","14":"INT APR","15":"INT APR","16":"INST APR","17":"INST APR","18":"NIGHT","19":"NIGHT","20":"ACTUAL INSTRUMENT","21":"ACTUAL INSTRUMENT","22":"SIMULATED INSTRUMENT (HOOD)","23":"SIMULATED INSTRUMENT (HOOD)","24":"FLIGHT SIMULATOR","25":"FLIGHT SIMULATOR","26":"CROSS COUNTRY","27":"CROSS COUNTRY","28":"AS FLIGHT INSTRUCTOR","29":"AS FLIGHT INSTRUCTOR","30":"DUAL RECEIVED","31":"DUAL RECEIVED","32":"PILOT IN COMMAND (INCL. SOLO)","33":"PILOT IN COMMAND (INCL. SOLO)","34":"TOTAL DURATION OF FLIGHT","35":"TOTAL DURATION OF FLIGHT"},"header":true},{"rowIndex":1,"content":{"1":"2/2","2":"C1725","3":"N678ND","4":"PHX","5":"SEA","6":"2","7":"avilliqué","8":"3","9":"3","10":"1","11":"5","12":"0","13":"0","14":"RNAV","15":"CHE","16":"VOR RW-15","17":"ClaZ","18":"0","19":"0","20":"0","21":"0","22":"0","23":"0","24":"0","25":"0","26":"1","27":"5","28":"0","29":"0","30":"0","31":"0","32":"1","33":"5","34":"1","35":"5"},"header":false}],"status":"SUCCESS","errorMessage":null}
